LICENSE
MANIFEST.in
README.md
setup.py
Mopidy_Grooveshark.egg-info/PKG-INFO
Mopidy_Grooveshark.egg-info/SOURCES.txt
Mopidy_Grooveshark.egg-info/dependency_links.txt
Mopidy_Grooveshark.egg-info/entry_points.txt
Mopidy_Grooveshark.egg-info/not-zip-safe
Mopidy_Grooveshark.egg-info/requires.txt
Mopidy_Grooveshark.egg-info/top_level.txt
mopidy_grooveshark/__init__.py
mopidy_grooveshark/backend.py
mopidy_grooveshark/ext.conf