Metadata-Version: 1.1
Name: Mopidy-Grooveshark
Version: 1.0.4
Summary: Mopidy extension that plays sound from Grooveshark
Home-page: https://github.com/camilonova/mopidy-grooveshark
Author: Camilo Nova
Author-email: camilo.nova@gmail.com
License: MIT
Platform: UNKNOWN
Classifier: Environment :: No Input/Output (Daemon)
Classifier: Intended Audience :: End Users/Desktop
Classifier: License :: OSI Approved :: MIT License
Classifier: Operating System :: OS Independent
Classifier: Programming Language :: Python :: 2
Classifier: Topic :: Multimedia :: Sound/Audio :: Players
